{
  "identifikasjonsnummer": [
    {
      "ajourholdstidspunkt": "2020-03-25T20:14:54.958+01:00",
      "erGjeldende": true,
      "kilde": "KILDE_DSF",
      "status": "iBruk",
      "foedselsEllerDNummer": "06086401477",
      "identifikatortype": "foedselsnummer"
    }
  ],
  "status": [
    {
      "ajourholdstidspunkt": "2020-03-25T20:14:54.958+01:00",
      "erGjeldende": true,
      "kilde": "KILDE_DSF",
      "gyldighetstidspunkt": "2020-03-25T20:14:54.958+01:00",
      "status": "bosatt"
    }
  ],
  "kjoenn": [
    {
      "erGjeldende": true,
      "kilde": "KILDE_DSF",
      "kjoenn": "kvinne"
    }
  ],
  "foedsel": [
    {
      "erGjeldende": true,
      "kilde": "KILDE_DSF",
      "foedselsdato": "1964-08-06",
      "foedselsaar": "1964",
      "foedekommuneINorge": "5401",
      "foedeland": "NOR"
    }
  ],
  "familierelasjon": [
    {
      "erGjeldende": true,
      "kilde": "KILDE_DSF",
      "relatertPerson": "12056502155",
      "relatertPersonsRolle": "ektefelleEllerPartner",
      "minRolleForPerson": "ektefelleEllerPartner"
    }
  ],
  "sivilstand": [
    {
      "erGjeldende": true,
      "kilde": "KILDE_DSF",
      "aarsak": "Vigsel",
      "gyldighetstidspunkt": "2020-03-24T00:00:00+01:00",
      "sivilstand": "gift",
      "sivilstandsdato": "2020-03-24",
      "relatertVedSivilstand": "12056502155"
    }
  ],
  "navn": [
    {
      "erGjeldende": true,
      "kilde": "KILDE_DSF",
      "aarsak": "Første gangs navnevalg",
      "gyldighetstidspunkt": "2019-01-01T00:00:00+01:00",
      "fornavn": "ANE",
      "etternavn": "JONES",
      "forkortetNavn": "ANE  JONES"
    }
  ],
  "bostedsadresse": [
    {
      "ajourholdstidspunkt": "2020-04-21T10:45:35.599+02:00",
      "erGjeldende": true,
      "kilde": "DataPatch",
      "gyldighetstidspunkt": "2020-04-21T10:45:35.599+02:00",
      "vegadresse": {
        "kommunenummer": "3025",
        "adressenavn": "Vendelåsen",
        "adressenummer": {
          "husnummer": "1",
          "husbokstav": "B"
        },
        "poststed": {
          "poststedsnavn": "NESØYA",
          "postnummer": "1397"
        }
      },
      "adressegradering": "ugradert"
    },
    {
      "ajourholdstidspunkt": "2020-04-21T10:32:39.685+02:00",
      "erGjeldende": false,
      "kilde": "DataPatch",
      "gyldighetstidspunkt": "2020-04-21T10:32:39.685+02:00",
      "vegadresse": {
        "kommunenummer": "5401",
        "adressenavn": "Nedre Storvollen",
        "adressenummer": {
          "husnummer": "34"
        },
        "poststed": {
          "poststedsnavn": "KVALØYA",
          "postnummer": "9104"
        }
      },
      "adressegradering": "ugradert"
    },
    {
      "ajourholdstidspunkt": "2020-03-24T00:00:00+01:00",
      "erGjeldende": false,
      "kilde": "KILDE_DSF",
      "aarsak": "Årsakskode fra DSF: ",
      "gyldighetstidspunkt": "2020-03-24T00:00:00+01:00",
      "vegadresse": {
        "kommunenummer": "5401",
        "bruksenhetsnummer": "H0101",
        "bruksenhetstype": "bolig",
        "adressenavn": "Storvolltunet",
        "adressekode": "00001",
        "poststed": {
          "poststedsnavn": "KVALØYA",
          "postnummer": "9104"
        },
        "coAdressenavn": ""
      },
      "adresseIdentifikatorFraMatrikkelen": "60758448",
      "adressegradering": "ugradert",
      "grunnkrets": 2042,
      "stemmekrets": 9,
      "skolekrets": 19,
      "kirkekrets": 1
    }
  ],
  "preferertKontaktadresse": [
    {
      "erGjeldende": true,
      "kilde": "",
      "valg": "postadresse",
      "adressegradering": "ugradert",
      "kontaktadresseIFrittFormat": {
        "adresselinje": [
          "STORVOLLTUNET",
          "9104 KVALØYA",
          "NORGE"
        ]
      }
    }
  ],
  "postadresse": [
    {
      "erGjeldende": true,
      "kilde": "KILDE_DSF",
      "gyldighetstidspunkt": "2020-03-24T00:00:00+01:00",
      "adressegradering": "ugradert",
      "postadresseIFrittFormat": {
        "adresselinje": [
          "Storvolltunet",
          "9104 KVALØYA",
          "Norge"
        ]
      }
    }
  ],
  "statsborgerskap": [
    {
      "erGjeldende": true,
      "kilde": "KILDE_DSF",
      "gyldighetstidspunkt": "2020-03-24T00:00:00+01:00",
      "statsborgerskap": "NOR",
      "ervervsdato": "2020-03-24"
    }
  ]
}