{
  "identifikasjonsnummer": [
    {
      "ajourholdstidspunkt": "2020-03-25T20:14:29.055+01:00",
      "erGjeldende": true,
      "kilde": "KILDE_DSF",
      "status": "iBruk",
      "foedselsEllerDNummer": "62014699681",
      "identifikatortype": "dNummer"
    }
  ],
  "status": [
    {
      "ajourholdstidspunkt": "2020-03-25T20:14:29.055+01:00",
      "erGjeldende": true,
      "kilde": "KILDE_DSF",
      "gyldighetstidspunkt": "2020-03-25T20:14:29.055+01:00",
      "status": "inaktiv"
    }
  ],
  "kjoenn": [
    {
      "erGjeldende": true,
      "kilde": "KILDE_DSF",
      "kjoenn": "kvinne"
    }
  ],
  "foedsel": [
    {
      "erGjeldende": true,
      "kilde": "KILDE_DSF",
      "foedselsdato": "1946-01-22",
      "foedselsaar": "1946"
    }
  ],
  "sivilstand": [
    {
      "erGjeldende": true,
      "kilde": "KILDE_DSF",
      "sivilstand": "gift"
    }
  ],
  "navn": [
    {
      "erGjeldende": true,
      "kilde": "KILDE_DSF",
      "fornavn": "PÅPASSELIGMATEMATISK",
      "mellomnavn": "AKTUELL",
      "etternavn": "TALLTEGN"
    }
  ],
  "oppholdsadresse": [
    {
      "ajourholdstidspunkt": "2020-04-15T18:38:07.181+02:00",
      "erGjeldende": true,
      "kilde": "DataPatch",
      "gyldighetstidspunkt": "2020-04-15T18:38:07.181+02:00",
      "vegadresse": {
        "kommunenummer": "3807",
        "adressenavn": "Kubrusvingen",
        "adressenummer": {
          "husnummer": "37"
        },
        "poststed": {
          "poststedsnavn": "SKIEN",
          "postnummer": "3729"
        }
      },
      "adressegradering": "ugradert"
    }
  ],
  "preferertKontaktadresse": [
    {
      "erGjeldende": true,
      "kilde": "",
      "valg": "postadresse",
      "adressegradering": "ugradert",
      "kontaktadresseIFrittFormat": {
        "adresselinje": [
          "LOUISEFARET 217NULL"
        ]
      }
    }
  ],
  "postadresse": [
    {
      "erGjeldende": true,
      "kilde": "KILDE_DSF",
      "gyldighetstidspunkt": "2020-03-24T00:00:00+01:00",
      "adressegradering": "ugradert",
      "postadresseIFrittFormat": {
        "adresselinje": [
          "Louisefaret 217null"
        ]
      }
    }
  ],
  "statsborgerskap": [
    {
      "erGjeldende": true,
      "kilde": "KILDE_DSF",
      "statsborgerskap": "NOR"
    }
  ]
}