{
  "identifikasjonsnummer": [
    {
      "ajourholdstidspunkt": "2020-03-25T20:15:49.598+01:00",
      "erGjeldende": true,
      "kilde": "KILDE_DSF",
      "status": "iBruk",
      "foedselsEllerDNummer": "21114300095",
      "identifikatortype": "foedselsnummer"
    }
  ],
  "status": [
    {
      "ajourholdstidspunkt": "2020-03-25T20:15:49.598+01:00",
      "erGjeldende": true,
      "kilde": "KILDE_DSF",
      "gyldighetstidspunkt": "2020-03-25T20:15:49.598+01:00",
      "status": "bosatt"
    }
  ],
  "kjoenn": [
    {
      "erGjeldende": true,
      "kilde": "KILDE_DSF",
      "kjoenn": "kvinne"
    }
  ],
  "foedsel": [
    {
      "erGjeldende": true,
      "kilde": "KILDE_DSF",
      "foedselsdato": "1943-11-21",
      "foedselsaar": "1943",
      "foedekommuneINorge": "5406",
      "foedeland": "NOR"
    }
  ],
  "navn": [
    {
      "erGjeldende": true,
      "kilde": "KILDE_DSF",
      "aarsak": "Første gangs navnevalg",
      "gyldighetstidspunkt": "2019-01-01T00:00:00+01:00",
      "fornavn": "MALI",
      "etternavn": "NISSEN",
      "forkortetNavn": "MALI  NISSEN"
    }
  ],
  "bostedsadresse": [
    {
      "ajourholdstidspunkt": "2020-04-21T11:06:09.521+02:00",
      "erGjeldende": true,
      "kilde": "DataPatch",
      "gyldighetstidspunkt": "2020-04-21T11:06:09.521+02:00",
      "vegadresse": {
        "kommunenummer": "0301",
        "adressenavn": "Haakon Tveters vei",
        "adressenummer": {
          "husnummer": "27"
        },
        "poststed": {
          "poststedsnavn": "OSLO",
          "postnummer": "0682"
        }
      },
      "adressegradering": "ugradert"
    },
    {
      "ajourholdstidspunkt": "2020-03-24T00:00:00+01:00",
      "erGjeldende": false,
      "kilde": "KILDE_DSF",
      "aarsak": "Årsakskode fra DSF: ",
      "gyldighetstidspunkt": "2020-03-24T00:00:00+01:00",
      "matrikkeladresse": {
        "bruksenhetsnummer": "H0101",
        "bruksenhetstype": "fritidsbolig",
        "matrikkelnummer": {
          "kommunenummer": "5406",
          "gaardsnummer": 123,
          "bruksnummer": 142,
          "festenummer": 0
        },
        "undernummer": 0,
        "poststed": {
          "poststedsnavn": "KVALSUND",
          "postnummer": "9620"
        }
      },
      "adresseIdentifikatorFraMatrikkelen": "139398580",
      "adressegradering": "ugradert",
      "grunnkrets": 606,
      "stemmekrets": 7,
      "skolekrets": 11,
      "kirkekrets": 1
    }
  ],
  "preferertKontaktadresse": [
    {
      "erGjeldende": true,
      "kilde": "",
      "valg": "bostedsadresse",
      "adressegradering": "ugradert",
      "kontaktadresseIFrittFormat": {
        "adresselinje": [
          "Haakon Tveters vei 27",
          "0682 OSLO"
        ]
      }
    }
  ],
  "statsborgerskap": [
    {
      "erGjeldende": true,
      "kilde": "KILDE_DSF",
      "gyldighetstidspunkt": "2020-03-24T00:00:00+01:00",
      "statsborgerskap": "NOR",
      "ervervsdato": "2020-03-24"
    }
  ]
}