{
  "identifikasjonsnummer": [
    {
      "ajourholdstidspunkt": "2020-03-25T20:16:17.24+01:00",
      "erGjeldende": true,
      "kilde": "KILDE_DSF",
      "status": "iBruk",
      "foedselsEllerDNummer": "31031503011",
      "identifikatortype": "foedselsnummer"
    }
  ],
  "status": [
    {
      "ajourholdstidspunkt": "2020-03-25T20:16:17.24+01:00",
      "erGjeldende": true,
      "kilde": "KILDE_DSF",
      "gyldighetstidspunkt": "2020-03-25T20:16:17.24+01:00",
      "status": "bosatt"
    }
  ],
  "kjoenn": [
    {
      "erGjeldende": true,
      "kilde": "KILDE_DSF",
      "kjoenn": "kvinne"
    }
  ],
  "foedsel": [
    {
      "erGjeldende": true,
      "kilde": "KILDE_DSF",
      "foedselsdato": "1915-03-31",
      "foedselsaar": "1915",
      "foedekommuneINorge": "1130",
      "foedeland": "NOR"
    }
  ],
  "navn": [
    {
      "erGjeldende": true,
      "kilde": "KILDE_DSF",
      "aarsak": "Første gangs navnevalg",
      "gyldighetstidspunkt": "2019-01-01T00:00:00+01:00",
      "fornavn": "DEMOKRATISK",
      "etternavn": "HANEFOLEEDDERKOPPKAMERA",
      "forkortetNavn": "DEMOKRATISK HANEFOLEEDDE."
    }
  ],
  "bostedsadresse": [
    {
      "ajourholdstidspunkt": "2020-03-25T00:00:00+01:00",
      "erGjeldende": true,
      "kilde": "KILDE_DSF",
      "aarsak": "Årsakskode fra DSF: ",
      "gyldighetstidspunkt": "2020-03-25T00:00:00+01:00",
      "matrikkeladresse": {
        "bruksenhetsnummer": "0",
        "matrikkelnummer": {
          "kommunenummer": "1130",
          "gaardsnummer": 48,
          "bruksnummer": 331,
          "festenummer": 0
        },
        "undernummer": 0,
        "poststed": {
          "poststedsnavn": "JØRPELAND",
          "postnummer": "4100"
        }
      },
      "adresseIdentifikatorFraMatrikkelen": "562111681",
      "adressegradering": "ugradert",
      "grunnkrets": 110,
      "stemmekrets": 5,
      "skolekrets": 4,
      "kirkekrets": 2
    },
    {
      "ajourholdstidspunkt": "2020-03-25T00:00:00+01:00",
      "erGjeldende": false,
      "kilde": "KILDE_DSF",
      "aarsak": "Flytting innen kommunen",
      "ukjentBosted": {
        "bostedskommune": "3420"
      },
      "adressegradering": "ugradert",
      "flyttedato": "0001-01-01"
    }
  ],
  "postadresse": [
    {
      "ajourholdstidspunkt": "2020-03-25T00:00:00+01:00",
      "erGjeldende": false,
      "kilde": "KILDE_DSF",
      "adressegradering": "ugradert",
      "postadresseIFrittFormat": {
        "adresselinje": [
          "Bringebærvegen",
          "2409 ELVERUM",
          "Norge"
        ]
      }
    }
  ],
  "statsborgerskap": [
    {
      "erGjeldende": true,
      "kilde": "KILDE_DSF",
      "gyldighetstidspunkt": "2020-03-25T00:00:00+01:00",
      "statsborgerskap": "NOR",
      "ervervsdato": "2020-03-25"
    }
  ]
}